<?xml version="1.0" encoding="utf-8"?>
<worldGeneration version="3"
				 xmlns="http://warpdrive.lemadec.org"
				 xmlns:xsi="http://www.w3.org/2001/XMLSchema-instance"
				 xsi:schemaLocation="http://warpdrive.lemadec.org WarpDrive.xsd"
				 mods="galacticraftcore">
	
	<!--
	  This Celestial Map is automatically selected when you have Galacticraft thanks to the worldGeneration.mods attribute.
	  Please refer to default celestialObjects XML file for extensive comments on how to read and modify this file format.
	  
	  This Celestial Map is a single star system for use with Galacticraft. If you also have MrLegend's ExtraPlanets, those planets will also be added.
	  Due to its oversized space size, this celestial map is better suited for Single player.
	  When reaching Jupiter or further, entities may take 'random' damage from suffocation in space due to Vanilla engine limitations when going further away from the center of a dimension (0 0).
	  
	  This map was initially made on scale for a 1.7.10 chinese audience. Original author is ???.
	  It was adapted since ported to 1.12.2 and integrated into the mod.
	  Positions and rendering are fairly basic to help you getting started.
	  -->
	
	<celestialObject id="Hyperspace">
		<size x="2000000" z="2000000" />
		<name>Hyperspace</name>
		<description>Your ship warp bubble is your\nonly protection.</description>
		
		<dimension id="-100" isBreathable="false" isHyperspace="true" gravity="legacyHyperspace">
			<center x="0" z="0" />
			<provider type="WarpDriveHyperspace" />
		</dimension>
		
		<skybox>
			<backgroundColor red="1.0" green="0.0" blue="0.0" />
			<starBrightnessBase>0.2</starBrightnessBase>
			<starBrightnessVanilla>0.0</starBrightnessVanilla>
			<celestialObjectOpacity>0.3</celestialObjectOpacity>
			<fogColor red="0.15" green="0.0" blue="0.0" />
			<fogFactor red="0.0" green="0.0" blue="0.0" />
		</skybox>
		
		<celestialObject id="solarSystem">
			<parent>
				<center x="0" z="0" />
			</parent>
			<size x="1900000" z="1900000" />
			<name>Solar system</name>
			<description>The void, filled with §6resources§r.</description>
			<dimension id="-101" isBreathable="false" gravity="legacySpace">
				<center x="0" z="0" />
				<provider type="WarpDriveSpace" />
				<generate group="moon" ratio="0.00125" />
				<generate group="asteroid" ratio="0.0067" />
				<generate group="asteroids_field" ratio="0.0016" />
			</dimension>
			
			<skybox>
				<backgroundColor red="0.0" green="0.0" blue="0.0" />
				<starBrightnessBase>0.9</starBrightnessBase>
				<starBrightnessVanilla>0.0</starBrightnessVanilla>
				<celestialObjectOpacity>1.0</celestialObjectOpacity>
				<fogColor red="0.0" green="0.0" blue="0.0" />
				<fogFactor red="0.0" green="0.0" blue="0.0" />
			</skybox>
			
			<celestialObject id="Sun">
				<parent>
					<center x="0" z="0" />
				</parent>
				<size x="10000" z="10000" />
				<render red="0.80" green="0.50" blue="0.20" alpha="1.00" texture="" />
				<render red="0.80" green="0.70" blue="0.30" alpha="0.40" texture="warpdrive:textures/celestial/surface_icy2.png" periodU="-20" periodV="104" additive="true" />
				<render red="0.80" green="0.55" blue="0.10" alpha="0.48" texture="warpdrive:textures/celestial/surface_metallic1.png" periodU="-40" periodV="140" additive="true" />
				<render red="0.80" green="0.45" blue="0.30" alpha="0.34" texture="warpdrive:textures/celestial/surface_magma1.png" periodU="24" periodV="-35" additive="true" />
				<render red="0.80" green="0.50" blue="0.20" alpha="0.08" texture="" />
				<render red="0.75" green="0.48" blue="0.20" alpha="0.08" texture="" />
				<render red="0.70" green="0.55" blue="0.20" alpha="0.08" texture="" />
			</celestialObject>
			
			<celestialObject id="Mercury" mods="extraplanets">
				<parent>
					<center x="15000" z="0" />
				</parent>
				<size x="5000" z="5000" />
				<dimension id="-13" isBreathable="false" gravity="normal">
					<center x="0" z="0" />
				</dimension>
				<render red="1.00" green="1.00" blue="1.00" alpha="1.00" texture="extraplanets:textures/blocks/mercury_surface.png" periodU="150" />
				<render red="0.80" green="0.90" blue="0.90" alpha="0.30" />
			</celestialObject>
			
			<celestialObject id="Venus" mods="galacticraftplanets">
				<parent>
					<center x="0" z="33000" />
				</parent>
				<size x="20000" z="20000" />
				<dimension id="-31" isBreathable="false" gravity="normal">
					<center x="0" z="0" />
				</dimension>
				<render red="1.00" green="1.00" blue="1.00" alpha="1.00" texture="galacticraftplanets:textures/blocks/venus_rock_0.png" periodU="150" />
				<render red="0.80" green="0.90" blue="0.90" alpha="0.30" />
			</celestialObject>
			
			<celestialObject id="Earth">
				<parent>
					<center x="-45000" z="0" />
				</parent>
				<size x="21000" z="21000" />
				<dimension id="0" isBreathable="true" gravity="normal">
					<center x="0" z="0" />
				</dimension>
				<render red="0.70" green="0.70" blue="0.70" alpha="1.00" texture="warpdrive:textures/celestial/surface_temperate2.png" />
				<render red="0.90" green="0.95" blue="1.00" alpha="0.15" texture="warpdrive:textures/celestial/cloud_small1.png" periodU="100" periodV="1100" additive="true" />
				<render red="0.90" green="0.90" blue="1.00" alpha="0.15" texture="warpdrive:textures/celestial/cloud_medium1.png" periodU="300" periodV="1500" additive="false" />
				<render red="0.80" green="0.70" blue="1.00" alpha="0.15" texture="warpdrive:textures/celestial/cloud_large1.png" periodU="500" periodV="2100" additive="false" />
				<render red="0.50" green="0.50" blue="1.00" alpha="0.08" />
				<render red="0.50" green="0.50" blue="1.00" alpha="0.08" />
				<render red="0.50" green="0.50" blue="1.00" alpha="0.08" />
				
				<celestialObject id="Hell">
					<parent>
						<center x="0" z="0" />
					</parent>
					<size x="5000" z="5000" />
					<dimension id="-1" isBreathable="true" gravity="normal">
						<center x="0" z="0" />
					</dimension>
				</celestialObject>
			</celestialObject>

			<celestialObject id="Moon">
				<parent>
					<center x="-65000" z="0" />
				</parent>
				<size x="6000" z="6000" />
				<dimension id="-28" isBreathable="false" gravity="normal">
					<center x="0" z="0" />
				</dimension>
				<render red="1.00" green="1.00" blue="1.00" alpha="1.00" texture="galacticraftcore:textures/gui/celestialbodies/moon.png" periodU="150" />
				<render red="0.80" green="0.90" blue="0.90" alpha="0.30" />
			</celestialObject>
			
			<celestialObject id="Mars">
				<parent>
					<center x="0" z="-86000" />
				</parent>
				<size x="11000" z="11000" />
				<dimension id="-29" isBreathable="false" gravity="normal">
					<center x="0" z="0" />
				</dimension>
				<render red="1.00" green="1.00" blue="1.00" alpha="1.00" texture="galacticraftcore:textures/gui/celestialbodies/mars.png" periodU="150" />
				<render red="0.80" green="0.90" blue="0.90" alpha="0.30" />
			</celestialObject>
			
			<celestialObject id="Phobos" mods="extraplanets">
				<parent>
					<center x="-10000" z="-96000" />
				</parent>
				<size x="5000" z="5000" />
				<dimension id="-1502" isBreathable="false" gravity="normal">
					<center x="0" z="0" />
				</dimension>
				<render red="1.00" green="1.00" blue="1.00" alpha="1.00" texture="extraplanets:textures/gui/celestialbodies/phobos.png" periodU="150" />
				<render red="0.80" green="0.90" blue="0.90" alpha="0.30" />
			</celestialObject>
			
			<celestialObject id="Deimos" mods="extraplanets">
				<parent>
					<center x="-18000" z="-104000" />
				</parent>
				<size x="3200" z="3200" />
				<dimension id="-1503" isBreathable="false" gravity="normal">
					<center x="0" z="0" />
				</dimension>
				<render red="1.00" green="1.00" blue="1.00" alpha="1.00" texture="extraplanets:textures/gui/celestialbodies/deimos.png" periodU="150" />
				<render red="0.80" green="0.90" blue="0.90" alpha="0.30" />
			</celestialObject>
			
			<celestialObject id="Asteroid belt" mods="extraplanets">
				<parent>
					<center x="146000" z="0" />
				</parent>
				<size x="15000" z="15000" />
				<dimension id="-30" isBreathable="false" gravity="normal">
					<center x="0" z="0" />
				</dimension>
				<render red="1.00" green="1.00" blue="1.00" alpha="1.00" texture="extraplanets:textures/blocks/ash_rock.png" periodU="150" />
				<render red="0.80" green="0.90" blue="0.90" alpha="0.30" />
			</celestialObject>
			
			<celestialObject id="Ceres\n谷神星" mods="extraplanets">
				<parent>
					<center x="146000" z="-10000" />
				</parent>
				<size x="2600" z="2600" />
				<dimension id="-20" isBreathable="false" gravity="normal">
					<center x="0" z="0" />
				</dimension>
				<render red="1.00" green="1.00" blue="1.00" alpha="1.00" texture="extraplanets:textures/gui/celestialbodies/ceres.png" periodU="150" />
				<render red="0.80" green="0.90" blue="0.90" alpha="0.30" />
			</celestialObject>
			
			<celestialObject id="Jupiter\n木星" mods="extraplanets">
				<parent>
					<center x="290000" z="0" />
				</parent>
				<size x="250000" z="250000" />
				<dimension id="-15" isBreathable="false" gravity="normal">
					<center x="0" z="0" />
				</dimension>
				<render red="1.00" green="1.00" blue="1.00" alpha="1.00" texture="extraplanets:textures/blocks/jupiter_surface.png" periodU="150" />
				<render red="0.80" green="0.90" blue="0.90" alpha="0.30" />
			</celestialObject>
			
			<celestialObject id="Io" mods="extraplanets">
				<parent>
					<center x="422000" z="-132000" />
				</parent>
				<size x="6000" z="6000" />
				<dimension id="-1500" isBreathable="false" gravity="0.43">
					<center x="0" z="0" />
				</dimension>
				<render red="1.00" green="1.00" blue="1.00" alpha="1.00" texture="extraplanets:textures/blocks/io_surface.png" periodU="150" />
				<render red="0.80" green="0.90" blue="0.90" alpha="0.30" />
			</celestialObject>
			
			<celestialObject id="Europa" mods="extraplanets">
				<parent>
					<center x="430000" z="-140000" />
				</parent>
				<size x="5000" z="5000" />
				<dimension id="-1501" isBreathable="false" gravity="0.4">
					<center x="0" z="0" />
				</dimension>
				<render red="1.00" green="1.00" blue="1.00" alpha="1.00" texture="extraplanets:textures/blocks/europa_surface.png" periodU="150" />
				<render red="0.80" green="0.90" blue="0.90" alpha="0.30" />
			</celestialObject>
			
			<celestialObject id="Ganymede" mods="extraplanets">
				<parent>
					<center x="443000" z="-153000" />
				</parent>
				<size x="9000" z="9000" />
				<dimension id="-1506" isBreathable="false" gravity="0.4">
					<center x="0" z="0" />
				</dimension>
				<render red="1.00" green="1.00" blue="1.00" alpha="1.00" texture="extraplanets:textures/blocks/ganymede_surface.png" periodU="150" />
				<render red="0.80" green="0.90" blue="0.90" alpha="0.30" />
			</celestialObject>
			
			<celestialObject id="Callisto" mods="extraplanets">
				<parent>
					<center x="458000" z="-168000" />
				</parent>
				<size x="8300" z="8300" />
				<dimension id="-1505" isBreathable="false" gravity="0.4">
					<center x="0" z="0" />
				</dimension>
				<render red="1.00" green="1.00" blue="1.00" alpha="1.00" texture="extraplanets:textures/blocks/callisto_surface.png" periodU="150" />
				<render red="0.80" green="0.90" blue="0.90" alpha="0.30" />
			</celestialObject>

			<celestialObject id="Saturn" mods="extraplanets">
				<parent>
					<center x="0" z="330000" />
				</parent>
				<size x="208000" z="208000" />
				<dimension id="-16" isBreathable="false" gravity="normal">
					<center x="0" z="0" />
				</dimension>
				<render red="1.00" green="1.00" blue="1.00" alpha="1.00" texture="extraplanets:textures/blocks/saturn_surface.png" periodU="150" />
				<render red="0.80" green="0.90" blue="0.90" alpha="0.30" />
			</celestialObject>
			
			<celestialObject id="Rhea" mods="extraplanets">
				<parent>
					<center x="116000" z="446000" />
				</parent>
				<size x="3600" z="3600" />
				<dimension id="-1507" isBreathable="false" gravity="0.3">
					<center x="0" z="0" />
				</dimension>
				<render red="1.00" green="1.00" blue="1.00" alpha="1.00" texture="extraplanets:textures/blocks/rhea_surface.png" periodU="150" />
				<render red="0.80" green="0.90" blue="0.90" alpha="0.30" />
			</celestialObject>
			
			<celestialObject id="Titan" mods="extraplanets">
				<parent>
					<center x="128000" z="458000" />
				</parent>
				<size x="8600" z="8600" />
				<dimension id="-1508" isBreathable="false" gravity="0.4">
					<center x="0" z="0" />
				</dimension>
				<render red="1.00" green="1.00" blue="1.00" alpha="1.00" texture="extraplanets:textures/blocks/titan_surface.png" periodU="150" />
				<render red="0.80" green="0.90" blue="0.90" alpha="0.30" />
			</celestialObject>
			
			<celestialObject id="Iapetus" mods="extraplanets">
				<parent>
					<center x="142000" z="472000" />
				</parent>
				<size x="2800" z="2800" />
				<dimension id="-1511" isBreathable="false" gravity="0.24">
					<center x="0" z="0" />
				</dimension>
				<render red="1.00" green="1.00" blue="1.00" alpha="1.00" texture="extraplanets:textures/blocks/iapetus_surface.png" periodU="150" />
				<render red="0.80" green="0.90" blue="0.90" alpha="0.30" />
			</celestialObject>
			
			<celestialObject id="Uranus" mods="extraplanets">
				<parent>
					<center x="-600000" z="0" />
				</parent>
				<size x="89000" z="89000" />
				<dimension id="-17" isBreathable="false" gravity="normal">
					<center x="0" z="0" />
				</dimension>
				<render red="1.00" green="1.00" blue="1.00" alpha="1.00" texture="extraplanets:textures/blocks/uranus_surface.png" periodU="150" />
				<render red="0.80" green="0.90" blue="0.90" alpha="0.30" />
			</celestialObject>
			
			<celestialObject id="Titania" mods="extraplanets">
				<parent>
					<center x="-653000" z="53000" />
				</parent>
				<size x="3200" z="3200" />
				<dimension id="-1510" isBreathable="false" gravity="0.6">
					<center x="0" z="0" />
				</dimension>
				<render red="1.00" green="1.00" blue="1.00" alpha="1.00" texture="extraplanets:textures/blocks/titania_surface.png" periodU="150" />
				<render red="0.80" green="0.90" blue="0.90" alpha="0.30" />
			</celestialObject>

			<celestialObject id="Oberon" mods="extraplanets">
				<parent>
					<center x="-661000" z="61000" />
				</parent>
				<size x="3200" z="3200" />
				<dimension id="-1509" isBreathable="false" gravity="0.6">
					<center x="0" z="0" />
				</dimension>
				<render red="1.00" green="1.00" blue="1.00" alpha="1.00" texture="extraplanets:textures/blocks/oberon_surface.png" periodU="150" />
				<render red="0.80" green="0.90" blue="0.90" alpha="0.30" />
			</celestialObject>
			
			<celestialObject id="Neptune" mods="extraplanets">
				<parent>
					<center x="0" z="-700000" />
				</parent>
				<size x="86602" z="86602" />
				<dimension id="-18" isBreathable="false" gravity="normal">
					<center x="0" z="0" />
				</dimension>
				<render red="1.00" green="1.00" blue="1.00" alpha="1.00" texture="extraplanets:textures/blocks/neptune_surface.png" periodU="150" />
				<render red="0.80" green="0.90" blue="0.90" alpha="0.30" />
			</celestialObject>
			
			<celestialObject id="Triton" mods="extraplanets">
				<parent>
					<center x="-58000" z="-758000" />
				</parent>
				<size x="5000" z="5000" />
				<dimension id="-1504" isBreathable="false" gravity="0.3">
					<center x="0" z="0" />
				</dimension>
				<render red="1.00" green="1.00" blue="1.00" alpha="1.00" texture="extraplanets:textures/blocks/triton_surface.png" periodU="150" />
				<render red="0.80" green="0.90" blue="0.90" alpha="0.30" />
			</celestialObject>
			
			<!-- Pluto is The End. It's a far planet. -->
			<celestialObject id="Pluto">
				<parent>
					<center x="-900000" z="0" />
				</parent>
				<size x="20000" z="20000" />
				<dimension id="1" isBreathable="true" gravity="normal">
					<center x="0" z="0" />
				</dimension>
				<render red="1.00" green="1.00" blue="1.00" alpha="1.00" texture="minecraft:textures/blocks/end_stone.png" periodU="150" />
				<render red="0.50" green="0.50" blue="0.40" alpha="0.30" />
			</celestialObject>
			
		</celestialObject>
		
	</celestialObject>
	
</worldGeneration>
